setuptools_ext.py
geiffg-1.1.1.dist-info/LICENSE
geiffg-1.1.1.dist-info/METADATA
geiffg-1.1.1.dist-info/WHEEL
geiffg-1.1.1.dist-info/top_level.txt
geiffg-1.1.1.dist-info/RECORD
