Metadata-Version: 2.2
Name: geiffg
Version: 1.1.1
Summary: Extension of setuptools to support all core metadata fields
Author: Wim Glenn
Author-email: hey@wimglenn.com
License: MIT
Project-URL: Homepage, https://github.com/wimglenn/setuptools-ext
Keywords: setuptools,packaging,metadata
Requires-Python: >=3.8
License-File: LICENSE
Requires-Dist: setuptools>=68.2.0
Requires-Dist: tomli; python_version < "3.11"
